[
    {
        "name_ch": "Canto",
        "date_price": "2023-07-14",
        "date_price1": "2023-07-07",
        "date_price2": "2023-07-14",
        "date_price3": "2023-07-13",
        "date_price4": "2023-07-06"
    },
    {
        "name_ch": "Evmos",
        "date_price": "2023-07-14",
        "date_price1": "2023-07-07",
        "date_price2": "2023-07-14",
        "date_price3": "2023-07-13",
        "date_price4": "2023-07-06"
    },
    {
        "name_ch": "Gravity",
        "date_price": "2023-07-14",
        "date_price1": "2023-07-07",
        "date_price2": "2023-07-14",
        "date_price3": "2023-07-13",
        "date_price4": "2023-07-06"
    },
    {
        "name_ch": "Meme",
        "date_price": "2023-07-14",
        "date_price1": "2023-07-14",
        "date_price2": "2023-07-14",
        "date_price3": "2023-07-13",
        "date_price4": "2023-07-11"
    },
    {
        "name_ch": "Rebus",
        "date_price": "2023-07-14",
        "date_price1": "2023-07-07",
        "date_price2": "2023-07-14",
        "date_price3": "2023-07-13",
        "date_price4": "2023-07-06"
    },
    {
        "name_ch": "Solana",
        "date_price": "2023-07-14",
        "date_price1": "2023-07-14",
        "date_price2": "2023-07-14",
        "date_price3": "2023-07-13",
        "date_price4": "2023-07-11"
    },
    {
        "name_ch": "Stride",
        "date_price": "2023-07-14",
        "date_price1": "2023-07-07",
        "date_price2": "2023-07-14",
        "date_price3": "2023-07-13",
        "date_price4": "2023-07-06"
    },
    {
        "name_ch": "Umee",
        "date_price": "2023-07-14",
        "date_price1": "2023-07-07",
        "date_price2": "2023-07-14",
        "date_price3": "2023-07-13",
        "date_price4": "2023-07-06"
    },
    {
        "name_ch": "Arable",
        "date_price": "2023-07-14",
        "date_price1": "2023-07-13",
        "date_price2": "2023-07-14",
        "date_price3": "2023-07-13",
        "date_price4": "2023-07-11"
    },
    {
        "name_ch": "Lambda",
        "date_price": "2023-07-14",
        "date_price1": "2023-07-14",
        "date_price2": "2023-07-14",
        "date_price3": "2023-07-13",
        "date_price4": "2023-07-11"
    },
    {
        "name_ch": "Gitopia",
        "date_price": "2023-07-14",
        "date_price1": "2023-07-14",
        "date_price2": "2023-07-14",
        "date_price3": "2023-07-13",
        "date_price4": "2023-07-11"
    },
    {
        "name_ch": "Aura",
        "date_price": "2023-07-14",
        "date_price1": "2023-07-14",
        "date_price2": "2023-07-14",
        "date_price3": "2023-07-13",
        "date_price4": "2023-07-11"
    },
    {
        "name_ch": "Humans",
        "date_price": "2023-07-14",
        "date_price1": "2023-07-14",
        "date_price2": "2023-07-14",
        "date_price3": "2023-07-13",
        "date_price4": "2023-07-11"
    },
    {
        "name_ch": "Quicksilver",
        "date_price": "2023-07-14",
        "date_price1": "2023-07-14",
        "date_price2": "2023-07-14",
        "date_price3": "2023-07-13",
        "date_price4": "2023-07-11"
    }
]